{
   "abstract" : "temporarily set Config or XSConfig values",
   "author" : [
      "Reini Urban <rurban@cpan.org>"
   ],
   "dynamic_config" : 0,
   "generated_by" : "ExtUtils::MakeMaker version 7.1, CPAN::Meta::Converter version 2.150005, CPAN::Meta::Converter version 2.150010",
   "license" : [
      "artistic_2"
   ],
   "meta-spec" : {
      "url" : "http://search.cpan.org/perldoc?CPAN::Meta::Spec",
      "version" : "2"
   },
   "name" : "Mock-Config",
   "no_index" : {
      "directory" : [
         "t",
         "inc"
      ]
   },
   "prereqs" : {
      "build" : {
         "requires" : {
            "Test::More" : "0"
         }
      },
      "configure" : {
         "requires" : {
            "ExtUtils::MakeMaker" : "0"
         }
      },
      "runtime" : {
         "requires" : {
            "perl" : "5.006"
         }
      }
   },
   "release_status" : "stable",
   "resources" : {
      "bugtracker" : {
         "web" : "https://github.com/perl11/Mock-Config/issues"
      },
      "license" : [
         "http://dev.perl.org/licenses/"
      ],
      "repository" : {
         "url" : "https://github.com/perl11/Mock-Config"
      }
   },
   "version" : "0.03",
   "x_serialization_backend" : "JSON::PP version 2.27400",
   "x_suggests" : {
      "XSConfig" : "6.19"
   }
}
